[
	{
		"pais" : 13,
		"descripcion" : "AFGANISTAN",
		"deszon" : null,
		"otros" : null,
		"pais_anb" : "AF",
		"continente" : 3,
		"pais_sis" : "AFG",
		"acuerdo" : "-",
		"rep_diplomatico" : "No"
	},
	{
		"pais" : 15,
		"descripcion" : "ALAND ISLAS",
		"deszon" : null,
		"otros" : null,
		"pais_anb" : "AX",
		"continente" : 4,
		"pais_sis" : "ALA",
		"acuerdo" : "-",
		"rep_diplomatico" : "No"
	},
	{
		"pais" : 17,
		"descripcion" : "ALBANIA",
		"deszon" : null,
		"otros" : null,
		"pais_anb" : "AL",
		"continente" : 4,
		"pais_sis" : "ALB",
		"acuerdo" : "-",
		"rep_diplomatico" : "No"
	},
	{
		"pais" : 23,
		"descripcion" : "ALEMANIA",
		"deszon" : null,
		"otros" : null,
		"pais_anb" : "DE",
		"continente" : 4,
		"pais_sis" : "DEU",
		"acuerdo" : "SGP-UE",
		"rep_diplomatico" : "Si"
	},
	{
		"pais" : 37,
		"descripcion" : "ANDORRA",
		"deszon" : null,
		"otros" : null,
		"pais_anb" : "AD",
		"continente" : 4,
		"pais_sis" : "AND",
		"acuerdo" : "-",
		"rep_diplomatico" : "No"
	},
	{
		"pais" : 40,
		"descripcion" : "ANGOLA",
		"deszon" : null,
		"otros" : null,
		"pais_anb" : "AO",
		"continente" : 1,
		"pais_sis" : "AGO",
		"acuerdo" : "-",
		"rep_diplomatico" : "No"
	},
	{
		"pais" : 41,
		"descripcion" : "ANGUILA",
		"deszon" : null,
		"otros" : null,
		"pais_anb" : "AI",
		"continente" : 2,
		"pais_sis" : "AIA",
		"acuerdo" : "-",
		"rep_diplomatico" : "No"
	},
	{
		"pais" : 43,
		"descripcion" : "ANTIGUA Y BARBUDA",
		"deszon" : null,
		"otros" : null,
		"pais_anb" : "AG",
		"continente" : 2,
		"pais_sis" : "ATG",
		"acuerdo" : "-",
		"rep_diplomatico" : "No"
	},
	{
		"pais" : 47,
		"descripcion" : "ANTILLAS HOLANDESAS",
		"deszon" : null,
		"otros" : null,
		"pais_anb" : "AN",
		"continente" : 2,
		"pais_sis" : "ANT",
		"acuerdo" : "-",
		"rep_diplomatico" : "No"
	},
	{
		"pais" : 53,
		"descripcion" : "ARABIA SAUDITA",
		"deszon" : null,
		"otros" : null,
		"pais_anb" : "SA",
		"continente" : 3,
		"pais_sis" : "SAU",
		"acuerdo" : "-",
		"rep_diplomatico" : "Gestion"
	},
	{
		"pais" : 59,
		"descripcion" : "ARGELIA",
		"deszon" : null,
		"otros" : null,
		"pais_anb" : "DZ",
		"continente" : 1,
		"pais_sis" : "DZA",
		"acuerdo" : "-",
		"rep_diplomatico" : "No"
	},
	{
		"pais" : 63,
		"descripcion" : "ARGENTINA",
		"deszon" : null,
		"otros" : null,
		"pais_anb" : "AR",
		"continente" : 2,
		"pais_sis" : "ARG",
		"acuerdo" : "ACE 36 MERCOSUR",
		"rep_diplomatico" : "Si"
	},
	{
		"pais" : 26,
		"descripcion" : "ARMENIA",
		"deszon" : null,
		"otros" : null,
		"pais_anb" : "AM",
		"continente" : 3,
		"pais_sis" : "ARM",
		"acuerdo" : "-",
		"rep_diplomatico" : "Gestion"
	},
	{
		"pais" : 27,
		"descripcion" : "ARUBA",
		"deszon" : null,
		"otros" : null,
		"pais_anb" : "AW",
		"continente" : 2,
		"pais_sis" : "ABW",
		"acuerdo" : "-",
		"rep_diplomatico" : "No"
	},
	{
		"pais" : 69,
		"descripcion" : "AUSTRALIA",
		"deszon" : null,
		"otros" : null,
		"pais_anb" : "AU",
		"continente" : 5,
		"pais_sis" : "AUS",
		"acuerdo" : "SGP-UE",
		"rep_diplomatico" : "Gestion"
	},
	{
		"pais" : 72,
		"descripcion" : "AUSTRIA",
		"deszon" : null,
		"otros" : null,
		"pais_anb" : "AT",
		"continente" : 4,
		"pais_sis" : "AUT",
		"acuerdo" : "-",
		"rep_diplomatico" : "Si"
	},
	{
		"pais" : 74,
		"descripcion" : "AZERBAIJAN",
		"deszon" : null,
		"otros" : null,
		"pais_anb" : "AZ",
		"continente" : 3,
		"pais_sis" : "AZE",
		"acuerdo" : "-",
		"rep_diplomatico" : "Gestion"
	},
	{
		"pais" : 77,
		"descripcion" : "BAHAMAS",
		"deszon" : null,
		"otros" : null,
		"pais_anb" : "BS",
		"continente" : 2,
		"pais_sis" : "BHS",
		"acuerdo" : "-",
		"rep_diplomatico" : "No"
	},
	{
		"pais" : 80,
		"descripcion" : "BAHREIM",
		"deszon" : null,
		"otros" : null,
		"pais_anb" : "BH",
		"continente" : 3,
		"pais_sis" : "BHR",
		"acuerdo" : "-",
		"rep_diplomatico" : "Gestion"
	},
	{
		"pais" : 81,
		"descripcion" : "BANGLADESH",
		"deszon" : null,
		"otros" : null,
		"pais_anb" : "BD",
		"continente" : 3,
		"pais_sis" : "BGD",
		"acuerdo" : "-",
		"rep_diplomatico" : "No"
	},
	{
		"pais" : 83,
		"descripcion" : "BARBADOS",
		"deszon" : null,
		"otros" : null,
		"pais_anb" : "BB",
		"continente" : 2,
		"pais_sis" : "BRB",
		"acuerdo" : "-",
		"rep_diplomatico" : "No"
	},
	{
		"pais" : 91,
		"descripcion" : "BIELORRUSIA",
		"deszon" : null,
		"otros" : null,
		"pais_anb" : "BY",
		"continente" : 4,
		"pais_sis" : "BLR",
		"acuerdo" : "SGP BIELORRUSIA",
		"rep_diplomatico" : "Gestion"
	},
	{
		"pais" : 87,
		"descripcion" : "BELGICA",
		"deszon" : null,
		"otros" : null,
		"pais_anb" : "BE",
		"continente" : 4,
		"pais_sis" : "BEL",
		"acuerdo" : "SGP-UE",
		"rep_diplomatico" : "Si"
	},
	{
		"pais" : 88,
		"descripcion" : "BELICE",
		"deszon" : null,
		"otros" : null,
		"pais_anb" : "BZ",
		"continente" : 2,
		"pais_sis" : "BLZ",
		"acuerdo" : "-",
		"rep_diplomatico" : "No"
	},
	{
		"pais" : 229,
		"descripcion" : "BENIN",
		"deszon" : null,
		"otros" : null,
		"pais_anb" : "BJ",
		"continente" : 1,
		"pais_sis" : "BEN",
		"acuerdo" : "-",
		"rep_diplomatico" : "No"
	},
	{
		"pais" : 90,
		"descripcion" : "BERMUDAS",
		"deszon" : null,
		"otros" : null,
		"pais_anb" : "BM",
		"continente" : 2,
		"pais_sis" : "BMU",
		"acuerdo" : "-",
		"rep_diplomatico" : "No"
	},
	{
		"pais" : 97,
		"descripcion" : "BOLIVIA",
		"deszon" : null,
		"otros" : null,
		"pais_anb" : "BO",
		"continente" : 2,
		"pais_sis" : "BOL",
		"acuerdo" : "-",
		"rep_diplomatico" : "No"
	},
	{
		"pais" : 29,
		"descripcion" : "BOSNIA Y HERZEGOVINA",
		"deszon" : null,
		"otros" : null,
		"pais_anb" : "BA",
		"continente" : 4,
		"pais_sis" : "BIH",
		"acuerdo" : "-",
		"rep_diplomatico" : "No"
	},
	{
		"pais" : 101,
		"descripcion" : "BOTSWANA",
		"deszon" : null,
		"otros" : null,
		"pais_anb" : "BW",
		"continente" : 1,
		"pais_sis" : "BWA",
		"acuerdo" : "-",
		"rep_diplomatico" : "No"
	},
	{
		"pais" : 105,
		"descripcion" : "BRASIL",
		"deszon" : null,
		"otros" : null,
		"pais_anb" : "BR",
		"continente" : 2,
		"pais_sis" : "BRA",
		"acuerdo" : "ACE 36 MERCOSUR",
		"rep_diplomatico" : "Si"
	},
	{
		"pais" : 108,
		"descripcion" : "BRUNEI DARUSSALAM",
		"deszon" : null,
		"otros" : null,
		"pais_anb" : "BN",
		"continente" : 3,
		"pais_sis" : "BRN",
		"acuerdo" : "-",
		"rep_diplomatico" : "No"
	},
	{
		"pais" : 111,
		"descripcion" : "BULGARIA",
		"deszon" : null,
		"otros" : null,
		"pais_anb" : "BG",
		"continente" : 4,
		"pais_sis" : "BGR",
		"acuerdo" : "SGP-UE",
		"rep_diplomatico" : "No"
	},
	{
		"pais" : 31,
		"descripcion" : "BURKINA FASO",
		"deszon" : null,
		"otros" : null,
		"pais_anb" : "BF",
		"continente" : 1,
		"pais_sis" : "BFA",
		"acuerdo" : "-",
		"rep_diplomatico" : "No"
	},
	{
		"pais" : 115,
		"descripcion" : "BURUNDI",
		"deszon" : null,
		"otros" : null,
		"pais_anb" : "BI",
		"continente" : 1,
		"pais_sis" : "BDI",
		"acuerdo" : "-",
		"rep_diplomatico" : "No"
	},
	{
		"pais" : 119,
		"descripcion" : "BUTAN",
		"deszon" : null,
		"otros" : null,
		"pais_anb" : "BT",
		"continente" : 3,
		"pais_sis" : "BTN",
		"acuerdo" : "-",
		"rep_diplomatico" : "No"
	},
	{
		"pais" : 127,
		"descripcion" : "CABO VERDE",
		"deszon" : null,
		"otros" : null,
		"pais_anb" : "CV",
		"continente" : 1,
		"pais_sis" : "CPV",
		"acuerdo" : "-",
		"rep_diplomatico" : "No"
	},
	{
		"pais" : 141,
		"descripcion" : "CAMBOYA",
		"deszon" : null,
		"otros" : null,
		"pais_anb" : "KH",
		"continente" : 3,
		"pais_sis" : "KHM",
		"acuerdo" : "-",
		"rep_diplomatico" : "No"
	},
	{
		"pais" : 145,
		"descripcion" : "CAMERUN",
		"deszon" : null,
		"otros" : null,
		"pais_anb" : "CM",
		"continente" : 1,
		"pais_sis" : "CMR",
		"acuerdo" : "-",
		"rep_diplomatico" : "No"
	},
	{
		"pais" : 149,
		"descripcion" : "CANADA",
		"deszon" : null,
		"otros" : null,
		"pais_anb" : "CA",
		"continente" : 2,
		"pais_sis" : "CAN",
		"acuerdo" : "SGP CANADA",
		"rep_diplomatico" : "Si"
	},
	{
		"pais" : 895,
		"descripcion" : "CANAL DE PANAMA",
		"deszon" : null,
		"otros" : null,
		"pais_anb" : "CP",
		"continente" : 2,
		"pais_sis" : "",
		"acuerdo" : "-",
		"rep_diplomatico" : "No"
	},
	{
		"pais" : 156,
		"descripcion" : "CEILAN",
		"deszon" : null,
		"otros" : null,
		"pais_anb" : "LK",
		"continente" : 3,
		"pais_sis" : "",
		"acuerdo" : "-",
		"rep_diplomatico" : "No"
	},
	{
		"pais" : 203,
		"descripcion" : "CHAD",
		"deszon" : null,
		"otros" : null,
		"pais_anb" : "TD",
		"continente" : 1,
		"pais_sis" : "TCD",
		"acuerdo" : "-",
		"rep_diplomatico" : "No"
	},
	{
		"pais" : 211,
		"descripcion" : "CHILE",
		"deszon" : null,
		"otros" : null,
		"pais_anb" : "CL",
		"continente" : 2,
		"pais_sis" : "CHL",
		"acuerdo" : "ACE 22",
		"rep_diplomatico" : "Si"
	},
	{
		"pais" : 215,
		"descripcion" : "CHINA",
		"deszon" : null,
		"otros" : null,
		"pais_anb" : "CN",
		"continente" : 3,
		"pais_sis" : "CHN",
		"acuerdo" : "-",
		"rep_diplomatico" : "Si"
	},
	{
		"pais" : 221,
		"descripcion" : "CHIPRE",
		"deszon" : null,
		"otros" : null,
		"pais_anb" : "CY",
		"continente" : 4,
		"pais_sis" : "CYP",
		"acuerdo" : "-",
		"rep_diplomatico" : "No"
	},
	{
		"pais" : 169,
		"descripcion" : "COLOMBIA",
		"deszon" : null,
		"otros" : null,
		"pais_anb" : "CO",
		"continente" : 2,
		"pais_sis" : "COL",
		"acuerdo" : "CAN",
		"rep_diplomatico" : "Si"
	},
	{
		"pais" : 173,
		"descripcion" : "COMORAS",
		"deszon" : null,
		"otros" : null,
		"pais_anb" : "KM",
		"continente" : 1,
		"pais_sis" : "COM",
		"acuerdo" : "-",
		"rep_diplomatico" : "No"
	},
	{
		"pais" : 177,
		"descripcion" : "REPUBLICA DEL CONGO",
		"deszon" : null,
		"otros" : null,
		"pais_anb" : "CG",
		"continente" : 1,
		"pais_sis" : "COG",
		"acuerdo" : "-",
		"rep_diplomatico" : "No"
	},
	{
		"pais" : 187,
		"descripcion" : "COREA DEL NORTE",
		"deszon" : null,
		"otros" : null,
		"pais_anb" : "KP",
		"continente" : 3,
		"pais_sis" : "PRK",
		"acuerdo" : "TLC",
		"rep_diplomatico" : "No"
	},
	{
		"pais" : 190,
		"descripcion" : "COREA DEL SUR",
		"deszon" : null,
		"otros" : null,
		"pais_anb" : "KR",
		"continente" : 3,
		"pais_sis" : "KOR",
		"acuerdo" : "TLC",
		"rep_diplomatico" : "Si"
	},
	{
		"pais" : 193,
		"descripcion" : "COSTA DEL MARFIL",
		"deszon" : null,
		"otros" : null,
		"pais_anb" : "CI",
		"continente" : 1,
		"pais_sis" : "CIV",
		"acuerdo" : "-",
		"rep_diplomatico" : "No"
	},
	{
		"pais" : 196,
		"descripcion" : "COSTA RICA",
		"deszon" : null,
		"otros" : null,
		"pais_anb" : "CR",
		"continente" : 2,
		"pais_sis" : "CRI",
		"acuerdo" : "-",
		"rep_diplomatico" : "Si"
	},
	{
		"pais" : 198,
		"descripcion" : "CROACIA",
		"deszon" : null,
		"otros" : null,
		"pais_anb" : "HR",
		"continente" : 4,
		"pais_sis" : "HRV",
		"acuerdo" : "-",
		"rep_diplomatico" : "No"
	},
	{
		"pais" : 199,
		"descripcion" : "CUBA",
		"deszon" : null,
		"otros" : null,
		"pais_anb" : "CU",
		"continente" : 2,
		"pais_sis" : "CUB",
		"acuerdo" : "ACE 47",
		"rep_diplomatico" : "Si"
	},
	{
		"pais" : 570,
		"descripcion" : "CURAZAO",
		"deszon" : null,
		"otros" : null,
		"pais_anb" : "CW",
		"continente" : 2,
		"pais_sis" : "CUW",
		"acuerdo" : "-",
		"rep_diplomatico" : "No"
	},
	{
		"pais" : 232,
		"descripcion" : "DINAMARCA",
		"deszon" : null,
		"otros" : null,
		"pais_anb" : "DK",
		"continente" : 4,
		"pais_sis" : "DNK",
		"acuerdo" : "SGP-UE",
		"rep_diplomatico" : "Si"
	},
	{
		"pais" : 783,
		"descripcion" : "DJIBOUTI",
		"deszon" : null,
		"otros" : null,
		"pais_anb" : "DJ",
		"continente" : 1,
		"pais_sis" : "DJI",
		"acuerdo" : "-",
		"rep_diplomatico" : "No"
	},
	{
		"pais" : 235,
		"descripcion" : "DOMINICA",
		"deszon" : null,
		"otros" : null,
		"pais_anb" : "DM",
		"continente" : 2,
		"pais_sis" : "DMA",
		"acuerdo" : "-",
		"rep_diplomatico" : "No"
	},
	{
		"pais" : 239,
		"descripcion" : "ECUADOR",
		"deszon" : null,
		"otros" : null,
		"pais_anb" : "EC",
		"continente" : 2,
		"pais_sis" : "ECU",
		"acuerdo" : "CAN",
		"rep_diplomatico" : "Si"
	},
	{
		"pais" : 240,
		"descripcion" : "EGIPTO",
		"deszon" : null,
		"otros" : null,
		"pais_anb" : "EG",
		"continente" : 1,
		"pais_sis" : "EGY",
		"acuerdo" : "-",
		"rep_diplomatico" : "Si"
	},
	{
		"pais" : 242,
		"descripcion" : "EL SALVADOR",
		"deszon" : null,
		"otros" : null,
		"pais_anb" : "SV",
		"continente" : 2,
		"pais_sis" : "SLV",
		"acuerdo" : "Centro America",
		"rep_diplomatico" : "Gestion"
	},
	{
		"pais" : 244,
		"descripcion" : "EMIRATOS ARABES UNIDOS",
		"deszon" : null,
		"otros" : null,
		"pais_anb" : "AE",
		"continente" : 3,
		"pais_sis" : "ARE",
		"acuerdo" : "-",
		"rep_diplomatico" : "Gestion"
	},
	{
		"pais" : 243,
		"descripcion" : "ERITREA",
		"deszon" : null,
		"otros" : null,
		"pais_anb" : "ER",
		"continente" : 1,
		"pais_sis" : "ERI",
		"acuerdo" : "-",
		"rep_diplomatico" : "No"
	},
	{
		"pais" : 246,
		"descripcion" : "ESLOVAQUIA",
		"deszon" : null,
		"otros" : null,
		"pais_anb" : "SK",
		"continente" : 4,
		"pais_sis" : "SVK",
		"acuerdo" : "SGP-UE",
		"rep_diplomatico" : "No"
	},
	{
		"pais" : 247,
		"descripcion" : "ESLOVENIA",
		"deszon" : null,
		"otros" : null,
		"pais_anb" : "SI",
		"continente" : 4,
		"pais_sis" : "SVN",
		"acuerdo" : "SGP-UE",
		"rep_diplomatico" : "No"
	},
	{
		"pais" : 245,
		"descripcion" : "ESPAÑA",
		"deszon" : null,
		"otros" : null,
		"pais_anb" : "ES",
		"continente" : 4,
		"pais_sis" : "ESP",
		"acuerdo" : "SGP-UE",
		"rep_diplomatico" : "Si"
	},
	{
		"pais" : 579,
		"descripcion" : "ESTADO DE PALESTINA",
		"deszon" : null,
		"otros" : null,
		"pais_anb" : "PS",
		"continente" : 3,
		"pais_sis" : "PSE",
		"acuerdo" : "-",
		"rep_diplomatico" : "No"
	},
	{
		"pais" : 249,
		"descripcion" : "ESTADOS UNIDOS",
		"deszon" : null,
		"otros" : null,
		"pais_anb" : "US",
		"continente" : 2,
		"pais_sis" : "USA",
		"acuerdo" : "SGP-EEUU",
		"rep_diplomatico" : "Si"
	},
	{
		"pais" : 251,
		"descripcion" : "ESTONIA",
		"deszon" : null,
		"otros" : null,
		"pais_anb" : "EE",
		"continente" : 4,
		"pais_sis" : "EST",
		"acuerdo" : "SGP-UE",
		"rep_diplomatico" : "No"
	},
	{
		"pais" : 253,
		"descripcion" : "ETIOPIA",
		"deszon" : null,
		"otros" : null,
		"pais_anb" : "ET",
		"continente" : 1,
		"pais_sis" : "ETH",
		"acuerdo" : "-",
		"rep_diplomatico" : "No"
	},
	{
		"pais" : 870,
		"descripcion" : "FIJI",
		"deszon" : null,
		"otros" : null,
		"pais_anb" : "FJ",
		"continente" : 5,
		"pais_sis" : "FJI",
		"acuerdo" : "-",
		"rep_diplomatico" : "No"
	},
	{
		"pais" : 267,
		"descripcion" : "FILIPINAS",
		"deszon" : null,
		"otros" : null,
		"pais_anb" : "PH",
		"continente" : 3,
		"pais_sis" : "PHL",
		"acuerdo" : "-",
		"rep_diplomatico" : "No"
	},
	{
		"pais" : 271,
		"descripcion" : "FINLANDIA",
		"deszon" : null,
		"otros" : null,
		"pais_anb" : "FI",
		"continente" : 4,
		"pais_sis" : "FIN",
		"acuerdo" : "SGP-UE",
		"rep_diplomatico" : "No"
	},
	{
		"pais" : 275,
		"descripcion" : "FRANCIA",
		"deszon" : null,
		"otros" : null,
		"pais_anb" : "FR",
		"continente" : 4,
		"pais_sis" : "FRA",
		"acuerdo" : "SGP-UE",
		"rep_diplomatico" : "Si"
	},
	{
		"pais" : 281,
		"descripcion" : "GABON",
		"deszon" : null,
		"otros" : null,
		"pais_anb" : "GA",
		"continente" : 1,
		"pais_sis" : "GAB",
		"acuerdo" : "-",
		"rep_diplomatico" : "No"
	},
	{
		"pais" : 285,
		"descripcion" : "GAMBIA",
		"deszon" : null,
		"otros" : null,
		"pais_anb" : "GM",
		"continente" : 1,
		"pais_sis" : "GMB",
		"acuerdo" : "-",
		"rep_diplomatico" : "No"
	},
	{
		"pais" : 287,
		"descripcion" : "GEORGIA",
		"deszon" : null,
		"otros" : null,
		"pais_anb" : "GE",
		"continente" : 4,
		"pais_sis" : "GEO",
		"acuerdo" : "-",
		"rep_diplomatico" : "No"
	},
	{
		"pais" : 992,
		"descripcion" : "GEORGIA DEL SUR Y SANDWICH DEL SUR, ISLAS",
		"deszon" : null,
		"otros" : null,
		"pais_anb" : "GS",
		"continente" : 3,
		"pais_sis" : "SGS",
		"acuerdo" : "-",
		"rep_diplomatico" : "No"
	},
	{
		"pais" : 289,
		"descripcion" : "GHANA",
		"deszon" : null,
		"otros" : null,
		"pais_anb" : "GH",
		"continente" : 1,
		"pais_sis" : "GHA",
		"acuerdo" : "-",
		"rep_diplomatico" : "No"
	},
	{
		"pais" : 293,
		"descripcion" : "GIBRALTAR",
		"deszon" : null,
		"otros" : null,
		"pais_anb" : "GI",
		"continente" : 4,
		"pais_sis" : "GIB",
		"acuerdo" : "-",
		"rep_diplomatico" : "No"
	},
	{
		"pais" : 297,
		"descripcion" : "GRANADA",
		"deszon" : null,
		"otros" : null,
		"pais_anb" : "GD",
		"continente" : 2,
		"pais_sis" : "GRD",
		"acuerdo" : "-",
		"rep_diplomatico" : "No"
	},
	{
		"pais" : 301,
		"descripcion" : "GRECIA",
		"deszon" : null,
		"otros" : null,
		"pais_anb" : "GR",
		"continente" : 4,
		"pais_sis" : "GRC",
		"acuerdo" : "SGP-UE",
		"rep_diplomatico" : "No"
	},
	{
		"pais" : 305,
		"descripcion" : "GROENLANDIA",
		"deszon" : null,
		"otros" : null,
		"pais_anb" : "GL",
		"continente" : 2,
		"pais_sis" : "GRL",
		"acuerdo" : "-",
		"rep_diplomatico" : "No"
	},
	{
		"pais" : 309,
		"descripcion" : "GUADALUPE",
		"deszon" : null,
		"otros" : null,
		"pais_anb" : "GP",
		"continente" : 2,
		"pais_sis" : "GLP",
		"acuerdo" : "-",
		"rep_diplomatico" : "No"
	},
	{
		"pais" : 313,
		"descripcion" : "GUAM",
		"deszon" : null,
		"otros" : null,
		"pais_anb" : "GU",
		"continente" : 5,
		"pais_sis" : "GUM",
		"acuerdo" : "-",
		"rep_diplomatico" : "No"
	},
	{
		"pais" : 317,
		"descripcion" : "GUATEMALA",
		"deszon" : null,
		"otros" : null,
		"pais_anb" : "GT",
		"continente" : 2,
		"pais_sis" : "GTM",
		"acuerdo" : "Centro America",
		"rep_diplomatico" : "Gestion"
	},
	{
		"pais" : 325,
		"descripcion" : "GUAYANA FRANCESA",
		"deszon" : null,
		"otros" : null,
		"pais_anb" : "GF",
		"continente" : 2,
		"pais_sis" : "GUF",
		"acuerdo" : "-",
		"rep_diplomatico" : "No"
	},
	{
		"pais" : 831,
		"descripcion" : "GUERNSEY",
		"deszon" : null,
		"otros" : null,
		"pais_anb" : "GG",
		"continente" : 4,
		"pais_sis" : "GGY",
		"acuerdo" : "-",
		"rep_diplomatico" : "No"
	},
	{
		"pais" : 329,
		"descripcion" : "GUINEA",
		"deszon" : null,
		"otros" : null,
		"pais_anb" : "GN",
		"continente" : 1,
		"pais_sis" : "GIN",
		"acuerdo" : "-",
		"rep_diplomatico" : "No"
	},
	{
		"pais" : 334,
		"descripcion" : "GUINEA - BISSAU",
		"deszon" : null,
		"otros" : null,
		"pais_anb" : "GW",
		"continente" : 1,
		"pais_sis" : "GNB",
		"acuerdo" : "-",
		"rep_diplomatico" : "No"
	},
	{
		"pais" : 331,
		"descripcion" : "GUINEA ECUATORIAL",
		"deszon" : null,
		"otros" : null,
		"pais_anb" : "GQ",
		"continente" : 1,
		"pais_sis" : "GNQ",
		"acuerdo" : "-",
		"rep_diplomatico" : "No"
	},
	{
		"pais" : 337,
		"descripcion" : "GUYANA",
		"deszon" : null,
		"otros" : null,
		"pais_anb" : "GY",
		"continente" : 2,
		"pais_sis" : "GNB",
		"acuerdo" : "-",
		"rep_diplomatico" : "No"
	},
	{
		"pais" : 341,
		"descripcion" : "HAITI",
		"deszon" : null,
		"otros" : null,
		"pais_anb" : "HT",
		"continente" : 2,
		"pais_sis" : "HTI",
		"acuerdo" : "-",
		"rep_diplomatico" : "No"
	},
	{
		"pais" : 573,
		"descripcion" : "HOLANDA",
		"deszon" : null,
		"otros" : null,
		"pais_anb" : "NL",
		"continente" : 4,
		"pais_sis" : "NLD",
		"acuerdo" : "SGP-UE",
		"rep_diplomatico" : "Si"
	},
	{
		"pais" : 345,
		"descripcion" : "HONDURAS",
		"deszon" : null,
		"otros" : null,
		"pais_anb" : "HN",
		"continente" : 2,
		"pais_sis" : "HND",
		"acuerdo" : "-",
		"rep_diplomatico" : "Gestion"
	},
	{
		"pais" : 351,
		"descripcion" : "HONG KONG",
		"deszon" : null,
		"otros" : null,
		"pais_anb" : "HK",
		"continente" : 3,
		"pais_sis" : "HKG",
		"acuerdo" : "-",
		"rep_diplomatico" : "No"
	},
	{
		"pais" : 355,
		"descripcion" : "HUNGRIA",
		"deszon" : null,
		"otros" : null,
		"pais_anb" : "HU",
		"continente" : 4,
		"pais_sis" : "HUN",
		"acuerdo" : "SGP-UE",
		"rep_diplomatico" : "No"
	},
	{
		"pais" : 361,
		"descripcion" : "INDIA",
		"deszon" : null,
		"otros" : null,
		"pais_anb" : "IN",
		"continente" : 3,
		"pais_sis" : "IND",
		"acuerdo" : "INDIA",
		"rep_diplomatico" : "Si"
	},
	{
		"pais" : 365,
		"descripcion" : "INDONESIA",
		"deszon" : null,
		"otros" : null,
		"pais_anb" : "ID",
		"continente" : 3,
		"pais_sis" : "IDN",
		"acuerdo" : "-",
		"rep_diplomatico" : "No"
	},
	{
		"pais" : 628,
		"descripcion" : "INGLATERRA",
		"deszon" : null,
		"otros" : null,
		"pais_anb" : "GB",
		"continente" : 4,
		"pais_sis" : "GBR",
		"acuerdo" : "SGP-UE",
		"rep_diplomatico" : "Si"
	},
	{
		"pais" : 369,
		"descripcion" : "IRAK",
		"deszon" : null,
		"otros" : null,
		"pais_anb" : "IQ",
		"continente" : 3,
		"pais_sis" : "IRQ",
		"acuerdo" : "-",
		"rep_diplomatico" : "No"
	},
	{
		"pais" : 372,
		"descripcion" : "IRAN",
		"deszon" : null,
		"otros" : null,
		"pais_anb" : "IR",
		"continente" : 3,
		"pais_sis" : "IRN",
		"acuerdo" : "-",
		"rep_diplomatico" : "Si"
	},
	{
		"pais" : 375,
		"descripcion" : "IRLANDA",
		"deszon" : null,
		"otros" : null,
		"pais_anb" : "IE",
		"continente" : 4,
		"pais_sis" : "IRL",
		"acuerdo" : "SGP-UE",
		"rep_diplomatico" : "No"
	},
	{
		"pais" : 991,
		"descripcion" : "ISLA BOUVET",
		"deszon" : null,
		"otros" : null,
		"pais_anb" : "BV",
		"continente" : 4,
		"pais_sis" : "BVT",
		"acuerdo" : "-",
		"rep_diplomatico" : "No"
	},
	{
		"pais" : 395,
		"descripcion" : "ISLA JOHNSTON",
		"deszon" : null,
		"otros" : null,
		"pais_anb" : "JT",
		"continente" : 5,
		"pais_sis" : "JTN",
		"acuerdo" : "-",
		"rep_diplomatico" : "No"
	},
	{
		"pais" : 501,
		"descripcion" : "ISLA MONTSERRAT",
		"deszon" : null,
		"otros" : null,
		"pais_anb" : "MS",
		"continente" : 2,
		"pais_sis" : "MSR",
		"acuerdo" : "-",
		"rep_diplomatico" : "No"
	},
	{
		"pais" : 511,
		"descripcion" : "ISLA NAVIDAD",
		"deszon" : null,
		"otros" : null,
		"pais_anb" : "CX",
		"continente" : 5,
		"pais_sis" : "CXR",
		"acuerdo" : "-",
		"rep_diplomatico" : "No"
	},
	{
		"pais" : 531,
		"descripcion" : "ISLA NIUE",
		"deszon" : null,
		"otros" : null,
		"pais_anb" : "NU",
		"continente" : 5,
		"pais_sis" : "NIU",
		"acuerdo" : "-",
		"rep_diplomatico" : "No"
	},
	{
		"pais" : 593,
		"descripcion" : "ISLA PITCAIRN",
		"deszon" : null,
		"otros" : null,
		"pais_anb" : "PN",
		"continente" : 5,
		"pais_sis" : "PCN",
		"acuerdo" : "-",
		"rep_diplomatico" : "No"
	},
	{
		"pais" : 379,
		"descripcion" : "ISLANDIA",
		"deszon" : null,
		"otros" : null,
		"pais_anb" : "IS",
		"continente" : 4,
		"pais_sis" : "ISL",
		"acuerdo" : "EFTA",
		"rep_diplomatico" : "Gestion"
	},
	{
		"pais" : 137,
		"descripcion" : "ISLAS CAIMAN",
		"deszon" : null,
		"otros" : null,
		"pais_anb" : "KY",
		"continente" : 2,
		"pais_sis" : "CYM",
		"acuerdo" : "-",
		"rep_diplomatico" : "No"
	},
	{
		"pais" : 155,
		"descripcion" : "ISLAS CANAL (NORMANDAS)",
		"deszon" : null,
		"otros" : null,
		"pais_anb" : "NN",
		"continente" : 4,
		"pais_sis" : "",
		"acuerdo" : "-",
		"rep_diplomatico" : "No"
	},
	{
		"pais" : 157,
		"descripcion" : "ISLAS CANTON Y ENDERBURRY",
		"deszon" : null,
		"otros" : null,
		"pais_anb" : "CT",
		"continente" : 0,
		"pais_sis" : "",
		"acuerdo" : "-",
		"rep_diplomatico" : "No"
	},
	{
		"pais" : 165,
		"descripcion" : "ISLAS COCOS (KEELING)",
		"deszon" : null,
		"otros" : null,
		"pais_anb" : "CC",
		"continente" : 5,
		"pais_sis" : "CCK",
		"acuerdo" : "-",
		"rep_diplomatico" : "No"
	},
	{
		"pais" : 183,
		"descripcion" : "ISLAS COOK",
		"deszon" : null,
		"otros" : null,
		"pais_anb" : "CK",
		"continente" : 5,
		"pais_sis" : "COK",
		"acuerdo" : "-",
		"rep_diplomatico" : "No"
	},
	{
		"pais" : 259,
		"descripcion" : "ISLAS FEROE",
		"deszon" : null,
		"otros" : null,
		"pais_anb" : "FO",
		"continente" : 4,
		"pais_sis" : "FRO",
		"acuerdo" : "-",
		"rep_diplomatico" : "No"
	},
	{
		"pais" : 993,
		"descripcion" : "ISLAS HEARD Y MC DONALD",
		"deszon" : null,
		"otros" : null,
		"pais_anb" : "HM",
		"continente" : 5,
		"pais_sis" : "HMD",
		"acuerdo" : "-",
		"rep_diplomatico" : "No"
	},
	{
		"pais" : 469,
		"descripcion" : "ISLAS MARIANAS DEL NORTE",
		"deszon" : null,
		"otros" : null,
		"pais_anb" : "MP",
		"continente" : 5,
		"pais_sis" : "",
		"acuerdo" : "-",
		"rep_diplomatico" : "No"
	},
	{
		"pais" : 472,
		"descripcion" : "ISLAS MARSHALL",
		"deszon" : null,
		"otros" : null,
		"pais_anb" : "MH",
		"continente" : 5,
		"pais_sis" : "",
		"acuerdo" : "-",
		"rep_diplomatico" : "No"
	},
	{
		"pais" : 566,
		"descripcion" : "ISLAS MENORES DE EE.UU.",
		"deszon" : null,
		"otros" : null,
		"pais_anb" : "UM",
		"continente" : 5,
		"pais_sis" : "UMI",
		"acuerdo" : "-",
		"rep_diplomatico" : "No"
	},
	{
		"pais" : 495,
		"descripcion" : "ISLAS MIDWAY",
		"deszon" : null,
		"otros" : null,
		"pais_anb" : "MI",
		"continente" : 5,
		"pais_sis" : "",
		"acuerdo" : "-",
		"rep_diplomatico" : "No"
	},
	{
		"pais" : 578,
		"descripcion" : "PALAU",
		"deszon" : null,
		"otros" : null,
		"pais_anb" : "PW",
		"continente" : 5,
		"pais_sis" : "",
		"acuerdo" : "-",
		"rep_diplomatico" : "No"
	},
	{
		"pais" : 677,
		"descripcion" : "ISLAS SALOMON",
		"deszon" : null,
		"otros" : null,
		"pais_anb" : "SB",
		"continente" : 5,
		"pais_sis" : "",
		"acuerdo" : "-",
		"rep_diplomatico" : "No"
	},
	{
		"pais" : 994,
		"descripcion" : "ISLAS SVALBARD Y JAN MAYEN",
		"deszon" : null,
		"otros" : null,
		"pais_anb" : "SJ",
		"continente" : 4,
		"pais_sis" : "",
		"acuerdo" : "-",
		"rep_diplomatico" : "No"
	},
	{
		"pais" : 823,
		"descripcion" : "ISLAS TURCAS Y CAICOS",
		"deszon" : null,
		"otros" : null,
		"pais_anb" : "TC",
		"continente" : 4,
		"pais_sis" : "TCA",
		"acuerdo" : "-",
		"rep_diplomatico" : "No"
	},
	{
		"pais" : 866,
		"descripcion" : "ISLAS VIRGENES (ESTADOS UNIDOS)",
		"deszon" : null,
		"otros" : null,
		"pais_anb" : "VI",
		"continente" : 2,
		"pais_sis" : "",
		"acuerdo" : "-",
		"rep_diplomatico" : "No"
	},
	{
		"pais" : 863,
		"descripcion" : "ISLAS VIRGENES (INGLATERRA)",
		"deszon" : null,
		"otros" : null,
		"pais_anb" : "VG",
		"continente" : 2,
		"pais_sis" : "",
		"acuerdo" : "-",
		"rep_diplomatico" : "No"
	},
	{
		"pais" : 875,
		"descripcion" : "ISLAS WALLIS Y FUTUNA",
		"deszon" : null,
		"otros" : null,
		"pais_anb" : "WF",
		"continente" : 5,
		"pais_sis" : "",
		"acuerdo" : "-",
		"rep_diplomatico" : "No"
	},
	{
		"pais" : 383,
		"descripcion" : "ISRAEL",
		"deszon" : null,
		"otros" : null,
		"pais_anb" : "IL",
		"continente" : 3,
		"pais_sis" : "ISR",
		"acuerdo" : "-",
		"rep_diplomatico" : "No"
	},
	{
		"pais" : 386,
		"descripcion" : "ITALIA",
		"deszon" : null,
		"otros" : null,
		"pais_anb" : "IT",
		"continente" : 4,
		"pais_sis" : "ITA",
		"acuerdo" : "SGP-UE",
		"rep_diplomatico" : "Si"
	},
	{
		"pais" : 391,
		"descripcion" : "JAMAICA",
		"deszon" : null,
		"otros" : null,
		"pais_anb" : "JM",
		"continente" : 2,
		"pais_sis" : "JAM",
		"acuerdo" : "-",
		"rep_diplomatico" : "No"
	},
	{
		"pais" : 399,
		"descripcion" : "JAPON",
		"deszon" : null,
		"otros" : null,
		"pais_anb" : "JP",
		"continente" : 3,
		"pais_sis" : "JPN",
		"acuerdo" : "SGP JAPON",
		"rep_diplomatico" : "Si"
	},
	{
		"pais" : 832,
		"descripcion" : "JERSEY",
		"deszon" : null,
		"otros" : null,
		"pais_anb" : "JE",
		"continente" : 4,
		"pais_sis" : "JEY",
		"acuerdo" : "-",
		"rep_diplomatico" : "No"
	},
	{
		"pais" : 403,
		"descripcion" : "JORDANIA",
		"deszon" : null,
		"otros" : null,
		"pais_anb" : "JO",
		"continente" : 3,
		"pais_sis" : "JOR",
		"acuerdo" : "-",
		"rep_diplomatico" : "No"
	},
	{
		"pais" : 406,
		"descripcion" : "KAZAJSTAN",
		"deszon" : null,
		"otros" : null,
		"pais_anb" : "KZ",
		"continente" : 3,
		"pais_sis" : "KAZ",
		"acuerdo" : "COMUNIDAD EUROASIATICA",
		"rep_diplomatico" : "Gestion"
	},
	{
		"pais" : 410,
		"descripcion" : "KENIA",
		"deszon" : null,
		"otros" : null,
		"pais_anb" : "KE",
		"continente" : 1,
		"pais_sis" : "KEN",
		"acuerdo" : "-",
		"rep_diplomatico" : "No"
	},
	{
		"pais" : 412,
		"descripcion" : "KIRGUISTÁN",
		"deszon" : null,
		"otros" : null,
		"pais_anb" : "KG",
		"continente" : 3,
		"pais_sis" : "",
		"acuerdo" : "-",
		"rep_diplomatico" : "Gestion"
	},
	{
		"pais" : 411,
		"descripcion" : "KIRIBATI",
		"deszon" : null,
		"otros" : null,
		"pais_anb" : "KI",
		"continente" : 5,
		"pais_sis" : "KIR",
		"acuerdo" : "-",
		"rep_diplomatico" : "No"
	},
	{
		"pais" : 413,
		"descripcion" : "KUWAIT",
		"deszon" : null,
		"otros" : null,
		"pais_anb" : "KW",
		"continente" : 3,
		"pais_sis" : "KWT",
		"acuerdo" : "-",
		"rep_diplomatico" : "No"
	},
	{
		"pais" : 420,
		"descripcion" : "LAOS",
		"deszon" : null,
		"otros" : null,
		"pais_anb" : "LA",
		"continente" : 3,
		"pais_sis" : "LAO",
		"acuerdo" : "-",
		"rep_diplomatico" : "Gestion"
	},
	{
		"pais" : 426,
		"descripcion" : "LESOTHO",
		"deszon" : null,
		"otros" : null,
		"pais_anb" : "LS",
		"continente" : 1,
		"pais_sis" : "LSO",
		"acuerdo" : "-",
		"rep_diplomatico" : "No"
	},
	{
		"pais" : 429,
		"descripcion" : "LETONIA",
		"deszon" : null,
		"otros" : null,
		"pais_anb" : "LV",
		"continente" : 4,
		"pais_sis" : "LVA",
		"acuerdo" : "SGP-UE",
		"rep_diplomatico" : "No"
	},
	{
		"pais" : 431,
		"descripcion" : "LIBANO",
		"deszon" : null,
		"otros" : null,
		"pais_anb" : "LB",
		"continente" : 3,
		"pais_sis" : "LBN",
		"acuerdo" : "-",
		"rep_diplomatico" : "No"
	},
	{
		"pais" : 434,
		"descripcion" : "LIBERIA",
		"deszon" : null,
		"otros" : null,
		"pais_anb" : "LR",
		"continente" : 1,
		"pais_sis" : "LBR",
		"acuerdo" : "-",
		"rep_diplomatico" : "No"
	},
	{
		"pais" : 438,
		"descripcion" : "LIBIA",
		"deszon" : null,
		"otros" : null,
		"pais_anb" : "LY",
		"continente" : 1,
		"pais_sis" : "LBY",
		"acuerdo" : "-",
		"rep_diplomatico" : "No"
	},
	{
		"pais" : 440,
		"descripcion" : "LIECHTENSTEIN",
		"deszon" : null,
		"otros" : null,
		"pais_anb" : "LI",
		"continente" : 4,
		"pais_sis" : "LIE",
		"acuerdo" : "EFTA",
		"rep_diplomatico" : "Gestion"
	},
	{
		"pais" : 443,
		"descripcion" : "LITUANIA",
		"deszon" : null,
		"otros" : null,
		"pais_anb" : "LT",
		"continente" : 4,
		"pais_sis" : "LTU",
		"acuerdo" : "SGP-UE",
		"rep_diplomatico" : "No"
	},
	{
		"pais" : 445,
		"descripcion" : "LUXEMBURGO",
		"deszon" : null,
		"otros" : null,
		"pais_anb" : "LU",
		"continente" : 4,
		"pais_sis" : "LUX",
		"acuerdo" : "SGP-UE",
		"rep_diplomatico" : "No"
	},
	{
		"pais" : 447,
		"descripcion" : "MACAO",
		"deszon" : null,
		"otros" : null,
		"pais_anb" : "MO",
		"continente" : 3,
		"pais_sis" : "MAC",
		"acuerdo" : "-",
		"rep_diplomatico" : "No"
	},
	{
		"pais" : 448,
		"descripcion" : "MACEDONIA",
		"deszon" : null,
		"otros" : null,
		"pais_anb" : "MK",
		"continente" : 4,
		"pais_sis" : "MKD",
		"acuerdo" : "-",
		"rep_diplomatico" : "No"
	},
	{
		"pais" : 450,
		"descripcion" : "MADAGASCAR",
		"deszon" : null,
		"otros" : null,
		"pais_anb" : "MG",
		"continente" : 1,
		"pais_sis" : "MDG",
		"acuerdo" : "-",
		"rep_diplomatico" : "No"
	},
	{
		"pais" : 455,
		"descripcion" : "MALASIA",
		"deszon" : null,
		"otros" : null,
		"pais_anb" : "MY",
		"continente" : 3,
		"pais_sis" : "MYS",
		"acuerdo" : "-",
		"rep_diplomatico" : "Gestion"
	},
	{
		"pais" : 458,
		"descripcion" : "MALAWI",
		"deszon" : null,
		"otros" : null,
		"pais_anb" : "MW",
		"continente" : 1,
		"pais_sis" : "MWI",
		"acuerdo" : "-",
		"rep_diplomatico" : "No"
	},
	{
		"pais" : 461,
		"descripcion" : "MALDIVAS",
		"deszon" : null,
		"otros" : null,
		"pais_anb" : "MV",
		"continente" : 3,
		"pais_sis" : "MDV",
		"acuerdo" : "-",
		"rep_diplomatico" : "No"
	},
	{
		"pais" : 464,
		"descripcion" : "MALI",
		"deszon" : null,
		"otros" : null,
		"pais_anb" : "ML",
		"continente" : 1,
		"pais_sis" : "MLI",
		"acuerdo" : "-",
		"rep_diplomatico" : "No"
	},
	{
		"pais" : 467,
		"descripcion" : "MALTA",
		"deszon" : null,
		"otros" : null,
		"pais_anb" : "MT",
		"continente" : 4,
		"pais_sis" : "MLT",
		"acuerdo" : "SGP-UE",
		"rep_diplomatico" : "No"
	},
	{
		"pais" : 474,
		"descripcion" : "MARRUECOS",
		"deszon" : null,
		"otros" : null,
		"pais_anb" : "MA",
		"continente" : 1,
		"pais_sis" : "MAR",
		"acuerdo" : "-",
		"rep_diplomatico" : "No"
	},
	{
		"pais" : 477,
		"descripcion" : "MARTINICA",
		"deszon" : null,
		"otros" : null,
		"pais_anb" : "MQ",
		"continente" : 2,
		"pais_sis" : "MTQ",
		"acuerdo" : "-",
		"rep_diplomatico" : "No"
	},
	{
		"pais" : 485,
		"descripcion" : "MAURICIO",
		"deszon" : null,
		"otros" : null,
		"pais_anb" : "MU",
		"continente" : 1,
		"pais_sis" : "MUS",
		"acuerdo" : "-",
		"rep_diplomatico" : "No"
	},
	{
		"pais" : 488,
		"descripcion" : "MAURITANIA",
		"deszon" : null,
		"otros" : null,
		"pais_anb" : "MR",
		"continente" : 1,
		"pais_sis" : "MRT",
		"acuerdo" : "-",
		"rep_diplomatico" : "No"
	},
	{
		"pais" : 175,
		"descripcion" : "MAYOTTE",
		"deszon" : null,
		"otros" : null,
		"pais_anb" : "YT",
		"continente" : 1,
		"pais_sis" : "MYT",
		"acuerdo" : "-",
		"rep_diplomatico" : "No"
	},
	{
		"pais" : 489,
		"descripcion" : "MAYOTTE",
		"deszon" : null,
		"otros" : null,
		"pais_anb" : "YT",
		"continente" : 1,
		"pais_sis" : "MYT",
		"acuerdo" : "-",
		"rep_diplomatico" : "No"
	},
	{
		"pais" : 493,
		"descripcion" : "MEXICO",
		"deszon" : null,
		"otros" : null,
		"pais_anb" : "MX",
		"continente" : 2,
		"pais_sis" : "MEX",
		"acuerdo" : "ACE 66",
		"rep_diplomatico" : "Si"
	},
	{
		"pais" : 494,
		"descripcion" : "MICRONESIA, ESTADOS FEDERADOS DE",
		"deszon" : null,
		"otros" : null,
		"pais_anb" : "FM",
		"continente" : 5,
		"pais_sis" : "",
		"acuerdo" : "-",
		"rep_diplomatico" : "No"
	},
	{
		"pais" : 496,
		"descripcion" : "MOLDAVIA",
		"deszon" : null,
		"otros" : null,
		"pais_anb" : "MD",
		"continente" : 4,
		"pais_sis" : "MDA",
		"acuerdo" : "-",
		"rep_diplomatico" : "No"
	},
	{
		"pais" : 498,
		"descripcion" : "MONACO",
		"deszon" : null,
		"otros" : null,
		"pais_anb" : "MC",
		"continente" : 4,
		"pais_sis" : "MCO",
		"acuerdo" : "-",
		"rep_diplomatico" : "No"
	},
	{
		"pais" : 497,
		"descripcion" : "MONGOLIA",
		"deszon" : null,
		"otros" : null,
		"pais_anb" : "MN",
		"continente" : 3,
		"pais_sis" : "MNG",
		"acuerdo" : "-",
		"rep_diplomatico" : "No"
	},
	{
		"pais" : 499,
		"descripcion" : "MONTENEGRO",
		"deszon" : null,
		"otros" : null,
		"pais_anb" : "ME",
		"continente" : 4,
		"pais_sis" : "MNE",
		"acuerdo" : "-",
		"rep_diplomatico" : "No"
	},
	{
		"pais" : 500,
		"descripcion" : "MONTENEGRO",
		"deszon" : null,
		"otros" : null,
		"pais_anb" : "ME",
		"continente" : 4,
		"pais_sis" : "MNE",
		"acuerdo" : "-",
		"rep_diplomatico" : "No"
	},
	{
		"pais" : 505,
		"descripcion" : "MOZAMBIQUE",
		"deszon" : null,
		"otros" : null,
		"pais_anb" : "MZ",
		"continente" : 1,
		"pais_sis" : "MOZ",
		"acuerdo" : "-",
		"rep_diplomatico" : "No"
	},
	{
		"pais" : 93,
		"descripcion" : "MYANMAR",
		"deszon" : null,
		"otros" : null,
		"pais_anb" : "MM",
		"continente" : 3,
		"pais_sis" : "MMR",
		"acuerdo" : "-",
		"rep_diplomatico" : "No"
	},
	{
		"pais" : 507,
		"descripcion" : "NAMIBIA",
		"deszon" : null,
		"otros" : null,
		"pais_anb" : "NA",
		"continente" : 1,
		"pais_sis" : "NAM",
		"acuerdo" : "-",
		"rep_diplomatico" : "No"
	},
	{
		"pais" : 508,
		"descripcion" : "NAURU",
		"deszon" : null,
		"otros" : null,
		"pais_anb" : "NR",
		"continente" : 5,
		"pais_sis" : "NRU",
		"acuerdo" : "-",
		"rep_diplomatico" : "No"
	},
	{
		"pais" : 517,
		"descripcion" : "NEPAL",
		"deszon" : null,
		"otros" : null,
		"pais_anb" : "NP",
		"continente" : 3,
		"pais_sis" : "NPL",
		"acuerdo" : "-",
		"rep_diplomatico" : "No"
	},
	{
		"pais" : 521,
		"descripcion" : "NICARAGUA",
		"deszon" : null,
		"otros" : null,
		"pais_anb" : "NI",
		"continente" : 2,
		"pais_sis" : "NIC",
		"acuerdo" : "ACE 70 ECO-ALBA",
		"rep_diplomatico" : "No"
	},
	{
		"pais" : 525,
		"descripcion" : "NIGER",
		"deszon" : null,
		"otros" : null,
		"pais_anb" : "NE",
		"continente" : 1,
		"pais_sis" : "NER",
		"acuerdo" : "-",
		"rep_diplomatico" : "No"
	},
	{
		"pais" : 528,
		"descripcion" : "NIGERIA",
		"deszon" : null,
		"otros" : null,
		"pais_anb" : "NG",
		"continente" : 1,
		"pais_sis" : "NGA",
		"acuerdo" : "-",
		"rep_diplomatico" : "No"
	},
	{
		"pais" : 999,
		"descripcion" : "NO DECLARADOS",
		"deszon" : null,
		"otros" : null,
		"pais_anb" : "..",
		"continente" : 0,
		"pais_sis" : "",
		"acuerdo" : "-",
		"rep_diplomatico" : "No"
	},
	{
		"pais" : 538,
		"descripcion" : "NORUEGA",
		"deszon" : null,
		"otros" : null,
		"pais_anb" : "NO",
		"continente" : 4,
		"pais_sis" : "NOR",
		"acuerdo" : "SGP-NORUEGA",
		"rep_diplomatico" : "Gestion"
	},
	{
		"pais" : 542,
		"descripcion" : "NUEVA CALEDONIA",
		"deszon" : null,
		"otros" : null,
		"pais_anb" : "NC",
		"continente" : 5,
		"pais_sis" : "NCL",
		"acuerdo" : "-",
		"rep_diplomatico" : "No"
	},
	{
		"pais" : 548,
		"descripcion" : "NUEVA ZELANDA",
		"deszon" : null,
		"otros" : null,
		"pais_anb" : "NZ",
		"continente" : 5,
		"pais_sis" : "NZL",
		"acuerdo" : "TLC",
		"rep_diplomatico" : "Gestion"
	},
	{
		"pais" : 787,
		"descripcion" : "OCEANO INDICO",
		"deszon" : null,
		"otros" : null,
		"pais_anb" : "IO",
		"continente" : 1,
		"pais_sis" : "",
		"acuerdo" : "-",
		"rep_diplomatico" : "No"
	},
	{
		"pais" : 556,
		"descripcion" : "OMAN",
		"deszon" : null,
		"otros" : null,
		"pais_anb" : "OM",
		"continente" : 3,
		"pais_sis" : "OMN",
		"acuerdo" : "-",
		"rep_diplomatico" : "No"
	},
	{
		"pais" : 576,
		"descripcion" : "PAKISTAN",
		"deszon" : null,
		"otros" : null,
		"pais_anb" : "PK",
		"continente" : 3,
		"pais_sis" : "PAK",
		"acuerdo" : "-",
		"rep_diplomatico" : "No"
	},
	{
		"pais" : 580,
		"descripcion" : "PANAMA",
		"deszon" : null,
		"otros" : null,
		"pais_anb" : "PA",
		"continente" : 2,
		"pais_sis" : "PAN",
		"acuerdo" : "PAR Panama",
		"rep_diplomatico" : "Si"
	},
	{
		"pais" : 545,
		"descripcion" : "PAPUA NUEVA GUINEA",
		"deszon" : null,
		"otros" : null,
		"pais_anb" : "PG",
		"continente" : 5,
		"pais_sis" : "PNG",
		"acuerdo" : "-",
		"rep_diplomatico" : "No"
	},
	{
		"pais" : 586,
		"descripcion" : "PARAGUAY",
		"deszon" : null,
		"otros" : null,
		"pais_anb" : "PY",
		"continente" : 2,
		"pais_sis" : "PRY",
		"acuerdo" : "ACE 36 MERCOSUR",
		"rep_diplomatico" : "Si"
	},
	{
		"pais" : 589,
		"descripcion" : "PERU",
		"deszon" : null,
		"otros" : null,
		"pais_anb" : "PE",
		"continente" : 2,
		"pais_sis" : "PER",
		"acuerdo" : "CAN",
		"rep_diplomatico" : "Si"
	},
	{
		"pais" : 599,
		"descripcion" : "POLINESIA FRANCESA",
		"deszon" : null,
		"otros" : null,
		"pais_anb" : "PF",
		"continente" : 5,
		"pais_sis" : "PYF",
		"acuerdo" : "-",
		"rep_diplomatico" : "No"
	},
	{
		"pais" : 603,
		"descripcion" : "POLONIA",
		"deszon" : null,
		"otros" : null,
		"pais_anb" : "PL",
		"continente" : 4,
		"pais_sis" : "POL",
		"acuerdo" : "SGP-UE",
		"rep_diplomatico" : "No"
	},
	{
		"pais" : 607,
		"descripcion" : "PORTUGAL",
		"deszon" : null,
		"otros" : null,
		"pais_anb" : "PT",
		"continente" : 4,
		"pais_sis" : "PRT",
		"acuerdo" : "SGP-UE",
		"rep_diplomatico" : "No"
	},
	{
		"pais" : 611,
		"descripcion" : "PUERTO RICO",
		"deszon" : null,
		"otros" : null,
		"pais_anb" : "PR",
		"continente" : 2,
		"pais_sis" : "PRI",
		"acuerdo" : "-",
		"rep_diplomatico" : "No"
	},
	{
		"pais" : 618,
		"descripcion" : "QATAR",
		"deszon" : null,
		"otros" : null,
		"pais_anb" : "QA",
		"continente" : 3,
		"pais_sis" : "",
		"acuerdo" : "-",
		"rep_diplomatico" : "Gestion"
	},
	{
		"pais" : 888,
		"descripcion" : "REPÚBLICA DEMOCRÁTICA DEL CONGO",
		"deszon" : null,
		"otros" : null,
		"pais_anb" : "CD",
		"continente" : 1,
		"pais_sis" : "COD",
		"acuerdo" : "-",
		"rep_diplomatico" : "No"
	},
	{
		"pais" : 640,
		"descripcion" : "REPUBLICA CENTROAFRICANA",
		"deszon" : null,
		"otros" : null,
		"pais_anb" : "CF",
		"continente" : 1,
		"pais_sis" : "CAF",
		"acuerdo" : "-",
		"rep_diplomatico" : "No"
	},
	{
		"pais" : 207,
		"descripcion" : "REPUBLICA CHECA",
		"deszon" : null,
		"otros" : null,
		"pais_anb" : "CZ",
		"continente" : 4,
		"pais_sis" : "",
		"acuerdo" : "-",
		"rep_diplomatico" : "No"
	},
	{
		"pais" : 644,
		"descripcion" : "REPUBLICA CHECA",
		"deszon" : null,
		"otros" : null,
		"pais_anb" : "CZ",
		"continente" : 4,
		"pais_sis" : "CZE",
		"acuerdo" : "SGP-UE",
		"rep_diplomatico" : "No"
	},
	{
		"pais" : 647,
		"descripcion" : "REPUBLICA DOMINICANA",
		"deszon" : null,
		"otros" : null,
		"pais_anb" : "DO",
		"continente" : 2,
		"pais_sis" : "DOM",
		"acuerdo" : "-",
		"rep_diplomatico" : "No"
	},
	{
		"pais" : 660,
		"descripcion" : "REUNION (ISLA)",
		"deszon" : null,
		"otros" : null,
		"pais_anb" : "RE",
		"continente" : 1,
		"pais_sis" : "REU",
		"acuerdo" : "-",
		"rep_diplomatico" : "No"
	},
	{
		"pais" : 675,
		"descripcion" : "RUANDA",
		"deszon" : null,
		"otros" : null,
		"pais_anb" : "RW",
		"continente" : 1,
		"pais_sis" : "RWA",
		"acuerdo" : "-",
		"rep_diplomatico" : "No"
	},
	{
		"pais" : 670,
		"descripcion" : "RUMANIA",
		"deszon" : null,
		"otros" : null,
		"pais_anb" : "RO",
		"continente" : 4,
		"pais_sis" : "ROU",
		"acuerdo" : "SGP-UE",
		"rep_diplomatico" : "No"
	},
	{
		"pais" : 676,
		"descripcion" : "RUSIA",
		"deszon" : null,
		"otros" : null,
		"pais_anb" : "RU",
		"continente" : 4,
		"pais_sis" : "RUS",
		"acuerdo" : "SGP RUSIA",
		"rep_diplomatico" : "Si"
	},
	{
		"pais" : 687,
		"descripcion" : "SAMOA",
		"deszon" : null,
		"otros" : null,
		"pais_anb" : "WS",
		"continente" : 5,
		"pais_sis" : "WSM",
		"acuerdo" : "-",
		"rep_diplomatico" : "No"
	},
	{
		"pais" : 690,
		"descripcion" : "SAMOA AMERICANA",
		"deszon" : null,
		"otros" : null,
		"pais_anb" : "AS",
		"continente" : 5,
		"pais_sis" : "ASM",
		"acuerdo" : "-",
		"rep_diplomatico" : "No"
	},
	{
		"pais" : 695,
		"descripcion" : "SAN  CRISTOBAL Y NIEVES",
		"deszon" : null,
		"otros" : null,
		"pais_anb" : "KN",
		"continente" : 2,
		"pais_sis" : "KNA",
		"acuerdo" : "-",
		"rep_diplomatico" : "No"
	},
	{
		"pais" : 705,
		"descripcion" : "SAN  VICENTE Y LAS GRANADINAS",
		"deszon" : null,
		"otros" : null,
		"pais_anb" : "VC",
		"continente" : 2,
		"pais_sis" : "",
		"acuerdo" : "-",
		"rep_diplomatico" : "No"
	},
	{
		"pais" : 652,
		"descripcion" : "SAN BARTOLOME",
		"deszon" : null,
		"otros" : null,
		"pais_anb" : "BL",
		"continente" : 0,
		"pais_sis" : "",
		"acuerdo" : "-",
		"rep_diplomatico" : "No"
	},
	{
		"pais" : 697,
		"descripcion" : "SAN MARINO",
		"deszon" : null,
		"otros" : null,
		"pais_anb" : "SM",
		"continente" : 4,
		"pais_sis" : "SMR",
		"acuerdo" : "-",
		"rep_diplomatico" : "No"
	},
	{
		"pais" : 700,
		"descripcion" : "SAN PEDRO Y MIQUELON",
		"deszon" : null,
		"otros" : null,
		"pais_anb" : "PM",
		"continente" : 2,
		"pais_sis" : "SPM",
		"acuerdo" : "-",
		"rep_diplomatico" : "No"
	},
	{
		"pais" : 710,
		"descripcion" : "SANTA HELENA",
		"deszon" : null,
		"otros" : null,
		"pais_anb" : "SH",
		"continente" : 1,
		"pais_sis" : "SHN",
		"acuerdo" : "-",
		"rep_diplomatico" : "No"
	},
	{
		"pais" : 715,
		"descripcion" : "SANTA LUCIA",
		"deszon" : null,
		"otros" : null,
		"pais_anb" : "LC",
		"continente" : 2,
		"pais_sis" : "LCA",
		"acuerdo" : "-",
		"rep_diplomatico" : "No"
	},
	{
		"pais" : 720,
		"descripcion" : "SANTO TOME Y PRINCIPE",
		"deszon" : null,
		"otros" : null,
		"pais_anb" : "ST",
		"continente" : 1,
		"pais_sis" : "STP",
		"acuerdo" : "-",
		"rep_diplomatico" : "No"
	},
	{
		"pais" : 728,
		"descripcion" : "SENEGAL",
		"deszon" : null,
		"otros" : null,
		"pais_anb" : "SN",
		"continente" : 1,
		"pais_sis" : "SEN",
		"acuerdo" : "-",
		"rep_diplomatico" : "No"
	},
	{
		"pais" : 688,
		"descripcion" : "SERBIA",
		"deszon" : null,
		"otros" : null,
		"pais_anb" : "RS",
		"continente" : 4,
		"pais_sis" : "SRB",
		"acuerdo" : "-",
		"rep_diplomatico" : "No"
	},
	{
		"pais" : 729,
		"descripcion" : "SERBIA",
		"deszon" : null,
		"otros" : null,
		"pais_anb" : "RS",
		"continente" : 4,
		"pais_sis" : "SRB",
		"acuerdo" : "-",
		"rep_diplomatico" : "No"
	},
	{
		"pais" : 731,
		"descripcion" : "SEYCHELLES",
		"deszon" : null,
		"otros" : null,
		"pais_anb" : "SC",
		"continente" : 1,
		"pais_sis" : "SYC",
		"acuerdo" : "-",
		"rep_diplomatico" : "No"
	},
	{
		"pais" : 735,
		"descripcion" : "SIERRA LEONA",
		"deszon" : null,
		"otros" : null,
		"pais_anb" : "SL",
		"continente" : 1,
		"pais_sis" : "SLE",
		"acuerdo" : "-",
		"rep_diplomatico" : "No"
	},
	{
		"pais" : 741,
		"descripcion" : "SINGAPUR",
		"deszon" : null,
		"otros" : null,
		"pais_anb" : "SG",
		"continente" : 3,
		"pais_sis" : "SGP",
		"acuerdo" : "-",
		"rep_diplomatico" : "Gestion"
	},
	{
		"pais" : 744,
		"descripcion" : "SIRIA",
		"deszon" : null,
		"otros" : null,
		"pais_anb" : "SY",
		"continente" : 3,
		"pais_sis" : "SYR",
		"acuerdo" : "-",
		"rep_diplomatico" : "Gestion"
	},
	{
		"pais" : 748,
		"descripcion" : "SOMALIA",
		"deszon" : null,
		"otros" : null,
		"pais_anb" : "SO",
		"continente" : 1,
		"pais_sis" : "SOM",
		"acuerdo" : "-",
		"rep_diplomatico" : "No"
	},
	{
		"pais" : 750,
		"descripcion" : "SRI LANKA",
		"deszon" : null,
		"otros" : null,
		"pais_anb" : "LK",
		"continente" : 3,
		"pais_sis" : "LKA",
		"acuerdo" : "-",
		"rep_diplomatico" : "No"
	},
	{
		"pais" : 756,
		"descripcion" : "SUDAFRICA",
		"deszon" : null,
		"otros" : null,
		"pais_anb" : "ZA",
		"continente" : 1,
		"pais_sis" : "ZAF",
		"acuerdo" : "SUDAFRICA",
		"rep_diplomatico" : "Gestion"
	},
	{
		"pais" : 759,
		"descripcion" : "SUDAN",
		"deszon" : null,
		"otros" : null,
		"pais_anb" : "SD",
		"continente" : 1,
		"pais_sis" : "SDN",
		"acuerdo" : "-",
		"rep_diplomatico" : "No"
	},
	{
		"pais" : 686,
		"descripcion" : "SUDAN DEL SUR",
		"deszon" : null,
		"otros" : null,
		"pais_anb" : "SS",
		"continente" : 0,
		"pais_sis" : "SSD",
		"acuerdo" : "-",
		"rep_diplomatico" : "No"
	},
	{
		"pais" : 764,
		"descripcion" : "SUECIA",
		"deszon" : null,
		"otros" : null,
		"pais_anb" : "SE",
		"continente" : 4,
		"pais_sis" : "SWE",
		"acuerdo" : "SGP-UE",
		"rep_diplomatico" : "Si"
	},
	{
		"pais" : 767,
		"descripcion" : "SUIZA",
		"deszon" : null,
		"otros" : null,
		"pais_anb" : "CH",
		"continente" : 4,
		"pais_sis" : "CHE",
		"acuerdo" : "SGP SUIZA",
		"rep_diplomatico" : "Si"
	},
	{
		"pais" : 770,
		"descripcion" : "SURINAM",
		"deszon" : null,
		"otros" : null,
		"pais_anb" : "SR",
		"continente" : 2,
		"pais_sis" : "SUR",
		"acuerdo" : "-",
		"rep_diplomatico" : "No"
	},
	{
		"pais" : 772,
		"descripcion" : "SVALBARD Y JAN MAYEN, ISLAS",
		"deszon" : null,
		"otros" : null,
		"pais_anb" : "SJ",
		"continente" : 0,
		"pais_sis" : "",
		"acuerdo" : "-",
		"rep_diplomatico" : "No"
	},
	{
		"pais" : 773,
		"descripcion" : "SWASILANDIA",
		"deszon" : null,
		"otros" : null,
		"pais_anb" : "SZ",
		"continente" : 1,
		"pais_sis" : "SWZ",
		"acuerdo" : "-",
		"rep_diplomatico" : "No"
	},
	{
		"pais" : 774,
		"descripcion" : "TADJIKISTAN",
		"deszon" : null,
		"otros" : null,
		"pais_anb" : "TJ",
		"continente" : 3,
		"pais_sis" : "",
		"acuerdo" : "-",
		"rep_diplomatico" : "Gestion"
	},
	{
		"pais" : 776,
		"descripcion" : "TAILANDIA",
		"deszon" : null,
		"otros" : null,
		"pais_anb" : "TH",
		"continente" : 3,
		"pais_sis" : "THA",
		"acuerdo" : "-",
		"rep_diplomatico" : "Gestion"
	},
	{
		"pais" : 218,
		"descripcion" : "TAIWAN, PROVINCIA DE CHINA",
		"deszon" : null,
		"otros" : null,
		"pais_anb" : "TW",
		"continente" : 3,
		"pais_sis" : "TWN",
		"acuerdo" : "-",
		"rep_diplomatico" : "No"
	},
	{
		"pais" : 780,
		"descripcion" : "REPUBLICA UNIDA DE TANZANIA",
		"deszon" : null,
		"otros" : null,
		"pais_anb" : "TZ",
		"continente" : 1,
		"pais_sis" : "TZA",
		"acuerdo" : "-",
		"rep_diplomatico" : "No"
	},
	{
		"pais" : 10,
		"descripcion" : "TERRITORIO  ANTARTICO BRITANICO",
		"deszon" : null,
		"otros" : null,
		"pais_anb" : "AQ",
		"continente" : 2,
		"pais_sis" : "",
		"acuerdo" : "-",
		"rep_diplomatico" : "No"
	},
	{
		"pais" : 786,
		"descripcion" : "TERRITORIO  ANTARTICO BRITANICO",
		"deszon" : null,
		"otros" : null,
		"pais_anb" : "AQ",
		"continente" : 4,
		"pais_sis" : "",
		"acuerdo" : "-",
		"rep_diplomatico" : "No"
	},
	{
		"pais" : 788,
		"descripcion" : "TIMOR DEL ESTE",
		"deszon" : null,
		"otros" : null,
		"pais_anb" : "TP",
		"continente" : 3,
		"pais_sis" : "",
		"acuerdo" : "-",
		"rep_diplomatico" : "No"
	},
	{
		"pais" : 800,
		"descripcion" : "TOGO",
		"deszon" : null,
		"otros" : null,
		"pais_anb" : "TG",
		"continente" : 1,
		"pais_sis" : "TGO",
		"acuerdo" : "-",
		"rep_diplomatico" : "No"
	},
	{
		"pais" : 805,
		"descripcion" : "TOKELAU",
		"deszon" : null,
		"otros" : null,
		"pais_anb" : "TK",
		"continente" : 5,
		"pais_sis" : "TKL",
		"acuerdo" : "-",
		"rep_diplomatico" : "No"
	},
	{
		"pais" : 810,
		"descripcion" : "TONGA",
		"deszon" : null,
		"otros" : null,
		"pais_anb" : "TO",
		"continente" : 5,
		"pais_sis" : "TON",
		"acuerdo" : "-",
		"rep_diplomatico" : "No"
	},
	{
		"pais" : 815,
		"descripcion" : "TRINIDAD Y TOBAGO",
		"deszon" : null,
		"otros" : null,
		"pais_anb" : "TT",
		"continente" : 2,
		"pais_sis" : "TTO",
		"acuerdo" : "-",
		"rep_diplomatico" : "No"
	},
	{
		"pais" : 820,
		"descripcion" : "TÚNEZ",
		"deszon" : null,
		"otros" : null,
		"pais_anb" : "TN",
		"continente" : 1,
		"pais_sis" : "TUN",
		"acuerdo" : "-",
		"rep_diplomatico" : "No"
	},
	{
		"pais" : 825,
		"descripcion" : "TURKMENISTAN",
		"deszon" : null,
		"otros" : null,
		"pais_anb" : "TM",
		"continente" : 3,
		"pais_sis" : "TKM",
		"acuerdo" : "-",
		"rep_diplomatico" : "Gestion"
	},
	{
		"pais" : 827,
		"descripcion" : "TURQUIA",
		"deszon" : null,
		"otros" : null,
		"pais_anb" : "TR",
		"continente" : 3,
		"pais_sis" : "TUR",
		"acuerdo" : "SGP TURQUIA",
		"rep_diplomatico" : "No"
	},
	{
		"pais" : 828,
		"descripcion" : "TUVALU",
		"deszon" : null,
		"otros" : null,
		"pais_anb" : "TV",
		"continente" : 5,
		"pais_sis" : "TUV",
		"acuerdo" : "-",
		"rep_diplomatico" : "No"
	},
	{
		"pais" : 830,
		"descripcion" : "UCRANIA",
		"deszon" : null,
		"otros" : null,
		"pais_anb" : "UA",
		"continente" : 4,
		"pais_sis" : "UKR",
		"acuerdo" : "-",
		"rep_diplomatico" : "No"
	},
	{
		"pais" : 833,
		"descripcion" : "UGANDA",
		"deszon" : null,
		"otros" : null,
		"pais_anb" : "UG",
		"continente" : 1,
		"pais_sis" : "UGA",
		"acuerdo" : "-",
		"rep_diplomatico" : "No"
	},
	{
		"pais" : 845,
		"descripcion" : "URUGUAY",
		"deszon" : null,
		"otros" : null,
		"pais_anb" : "UY",
		"continente" : 2,
		"pais_sis" : "URY",
		"acuerdo" : "ACE 36 MERCOSUR",
		"rep_diplomatico" : "Si"
	},
	{
		"pais" : 847,
		"descripcion" : "UZBEKISTAN",
		"deszon" : null,
		"otros" : null,
		"pais_anb" : "UZ",
		"continente" : 3,
		"pais_sis" : "UZB",
		"acuerdo" : "-",
		"rep_diplomatico" : "Gestion"
	},
	{
		"pais" : 551,
		"descripcion" : "VANUATU",
		"deszon" : null,
		"otros" : null,
		"pais_anb" : "VU",
		"continente" : 0,
		"pais_sis" : "VUT",
		"acuerdo" : "-",
		"rep_diplomatico" : "No"
	},
	{
		"pais" : 159,
		"descripcion" : "VATICANO",
		"deszon" : null,
		"otros" : null,
		"pais_anb" : "VA",
		"continente" : 4,
		"pais_sis" : "VAT",
		"acuerdo" : "-",
		"rep_diplomatico" : "No"
	},
	{
		"pais" : 850,
		"descripcion" : "VENEZUELA",
		"deszon" : null,
		"otros" : null,
		"pais_anb" : "VE",
		"continente" : 2,
		"pais_sis" : "VEN",
		"acuerdo" : "ACE 70 ECO-ALBA",
		"rep_diplomatico" : "Si"
	},
	{
		"pais" : 855,
		"descripcion" : "VIET-NAM",
		"deszon" : null,
		"otros" : null,
		"pais_anb" : "VN",
		"continente" : 3,
		"pais_sis" : "VNM",
		"acuerdo" : "VIET-NAM",
		"rep_diplomatico" : "Gestion"
	},
	{
		"pais" : 880,
		"descripcion" : "YEMEN",
		"deszon" : null,
		"otros" : null,
		"pais_anb" : "YE",
		"continente" : 3,
		"pais_sis" : "YEM",
		"acuerdo" : "-",
		"rep_diplomatico" : "No"
	},
	{
		"pais" : 885,
		"descripcion" : "YUGOSLAVIA",
		"deszon" : null,
		"otros" : null,
		"pais_anb" : "YU",
		"continente" : 4,
		"pais_sis" : "YUG",
		"acuerdo" : "-",
		"rep_diplomatico" : "No"
	},
	{
		"pais" : 890,
		"descripcion" : "ZAMBIA",
		"deszon" : null,
		"otros" : null,
		"pais_anb" : "ZM",
		"continente" : 1,
		"pais_sis" : "ZMB",
		"acuerdo" : "-",
		"rep_diplomatico" : "No"
	},
	{
		"pais" : 665,
		"descripcion" : "ZIMBABWE",
		"deszon" : null,
		"otros" : null,
		"pais_anb" : "ZW",
		"continente" : 1,
		"pais_sis" : "",
		"acuerdo" : "-",
		"rep_diplomatico" : "No"
	},
	{
		"pais" : 990,
		"descripcion" : "ZONA FRANCA DE BOLIVIA",
		"deszon" : null,
		"otros" : null,
		"pais_anb" : "ZF",
		"continente" : 2,
		"pais_sis" : "",
		"acuerdo" : "-",
		"rep_diplomatico" : "No"
	},
	{
		"pais" : 535,
		"descripcion" : "ISLA NORFOLK",
		"deszon" : "OCEANIA",
		"otros" : null,
		"pais_anb" : "NF",
		"continente" : 5,
		"pais_sis" : null,
		"acuerdo" : "-",
		"rep_diplomatico" : "No"
	},
	{
		"pais" : 685,
		"descripcion" : "SAHARA OCCIDENTAL",
		"deszon" : "RESTO DE AFRICA",
		"otros" : null,
		"pais_anb" : "EH",
		"continente" : 1,
		"pais_sis" : "ESH",
		"acuerdo" : "-",
		"rep_diplomatico" : "No"
	},
	{
		"pais" : 238,
		"descripcion" : "FALKLAND ISLAS (MALVINAS)",
		"deszon" : "OTRAS",
		"otros" : null,
		"pais_anb" : "FK",
		"continente" : 2,
		"pais_sis" : "FLK",
		"acuerdo" : "-",
		"rep_diplomatico" : "No"
	},
	{
		"pais" : 933,
		"descripcion" : "ISLA DE MAN",
		"deszon" : "OTRAS",
		"otros" : null,
		"pais_anb" : "IM",
		"continente" : 4,
		"pais_sis" : "IMN",
		"acuerdo" : "-",
		"rep_diplomatico" : "No"
	},
	{
		"pais" : 901,
		"descripcion" : "KOSOVO",
		"deszon" : "RESTO DE EUROPA",
		"otros" : null,
		"pais_anb" : "XK",
		"continente" : 4,
		"pais_sis" : "XKX",
		"acuerdo" : "-",
		"rep_diplomatico" : "No"
	},
	{
		"pais" : 343,
		"descripcion" : "HEARD Y MC DONALD, ISLAS",
		"deszon" : "OCEANIA",
		"otros" : null,
		"pais_anb" : "HM",
		"continente" : 5,
		"pais_sis" : "HMD",
		"acuerdo" : "-",
		"rep_diplomatico" : "No"
	},
	{
		"pais" : 102,
		"descripcion" : "ISLA BOUVET",
		"deszon" : "RESTO DE AFRICA",
		"otros" : null,
		"pais_anb" : "BV",
		"continente" : 1,
		"pais_sis" : "BVT",
		"acuerdo" : "-",
		"rep_diplomatico" : "No"
	}
]
