[
    {
        "numero": "LEY 1489",
        "fecha": "1993-04-16",
        "titulo": "Ley de exportaciones",
        "archivo": "pdf/LEY_1489_de_16-04-1993.pdf",
        "descripcion": "La presente Ley alcanza a todas las mercancías y servicios del Universo Arancelario. Quedan fuera del alcance de esta Ley, aquellas mercancías y servicios, objeto de legislación específica, con excepción de los que corresponden al sector minero-metalúrgico",
        "seccion_de_norma_id": "1"
    },
    {
        "numero": "DS 29524",
        "fecha": "2008-04-18",
        "titulo": "Regulación de Aceite de soya",
        "archivo": "pdf/DS_29524_de_18-04-2008.pdf",
        "descripcion": "El presente Decreto Supremo tiene por objeto autorizar la exportación de los productos detallados a continuación, previa verificación de suficiencia de abastecimiento en el mercado interno a precio justo",
        "seccion_de_norma_id": "1"
    },
    {
        "numero": "DS 0373",
        "fecha": "2009-12-02",
        "titulo": "Regulación de Arroz",
        "archivo": "pdf/DS_0373_de_02-12-2009.pdf",
        "descripcion": "El presente Decreto Supremo tiene por objeto regular la exportación de los siguientes productos de Arroz, previa verificación de suficiencia de abastecimiento en el mercado interno a precio justo",
        "seccion_de_norma_id": "1"
    },
    {
        "numero": "DS 0501",
        "fecha": "2010-05-05",
        "titulo": "Regulación de Maíz para siembra",
        "archivo": "pdf/DS_0501_de_05-05-2010.pdf",
        "descripcion": "El presente Decreto Supremo tiene por objeto dejar sin efecto la suspensión temporal de exportación de maíz para siembra, previa verificación de suficiencia de abastecimiento en el mercado interno a precio justo",
        "seccion_de_norma_id": "1"
    },
    {
        "numero": "DS 0725",
        "fecha": "2010-12-06",
        "titulo": "Regulación de Harina de soya-Torta de girasol",
        "archivo": "pdf/DS_0725_de_06-12-2010.pdf",
        "descripcion": "El presente Decreto Supremo tiene por objeto regular la exportación de los siguientes productos, previa verificación de suficiencia de abastecimiento en el mercado interno y precio justo",
        "seccion_de_norma_id": "1"
    },
    {
        "numero": "DS 893",
        "fecha": "2011-06-01",
        "titulo": "Regulación de Azúcar",
        "archivo": "pdf/DS_893_de_01-06-2011.pdf",
        "descripcion": "Se autoriza de manera excepcional la exportación hasta un máximo de sesenta mil (60.000) toneladas de caña de azúcar, clasificada en la sub-partida arancelaria 1212.99.10.00, proveniente de la región de Bermejo",
        "seccion_de_norma_id": "1"
    },
    {
        "numero": "DS 1111",
        "fecha": "2011-12-21",
        "titulo": "Regulación de Azúcar",
        "archivo": "pdf/DS_1111_de_21-12-2011.pdf",
        "descripcion": "El presente Decreto Supremo, tiene por objeto autorizar de manera excepcional la exportación de azúcar hasta un máximo de treinta y dos mil quinientas (32.500) toneladas, clasificada en las subpartidas arancelarias 1701.11.90.00 y/o 1701.99.90.00, previa verificación de suficiencia de abastecimiento en el mercado interno a precio justo",
        "seccion_de_norma_id": "1"
    },
    {
        "numero": "DS 1163",
        "fecha": "2012-03-14",
        "titulo": "Regulación de Carne de res-Maiz-Arroz",
        "archivo": "pdf/DS_1163_de_14-03-2012.pdf",
        "descripcion": "El presente Decreto Supremo tiene por objeto autorizar la exportación de arroz, carne de res y maíz amarillo duro",
        "seccion_de_norma_id": "1"
    },
    {
        "numero": "DS 1223",
        "fecha": "2012-05-09",
        "titulo": "Regulación de Maíz",
        "archivo": "pdf/DS_1223_de_09-05-2012.pdf",
        "descripcion": "1. Suspender temporalmente la tramitación del certificado de exportación a precio justo de las exportaciones de girasol y sus derivados, y; 2. Ampliar el cupo de exportación de maíz amarillo duro de treinta mil (30.000) toneladas métricas hasta un máximo de sesenta mil (60.000) toneladas métricas, establecido en el Parágrafo III del Artículo 2 del Decreto Supremo Nro. 1163, de 14 de marzo de 2012",
        "seccion_de_norma_id": "1"
    },
    {
        "numero": "DS 1283",
        "fecha": "7/4/12",
        "titulo": "Regulación de Sorgo",
        "archivo": "pdf/DS_1283_de_04-07-2012.pdf",
        "descripcion": "El presente Decreto Supremo tiene por objeto exceptuar temporalmente la presentación del Certificado de Abastecimiento Interno y Precio Justo previo a la exportación de soya ante la Aduana Nacional; y autorizar l a exportación de sorgo, previa Certificación de Abastecimiento Interno y Precio Justo",
        "seccion_de_norma_id": "1"
    },
    {
        "numero": "DS 1324",
        "fecha": "2012-08-15",
        "titulo": "Regulación de Azucar cuota USA",
        "archivo": "pdf/DS_1324_de_15-08-2012.pdf",
        "descripcion": "El presente Decreto Supremo, tiene por objeto autorizar de manera excepcional la exportación de azúcar previa verificación de suficiencia de abastecimiento en el mercado interno a precio justo",
        "seccion_de_norma_id": "1"
    },
    {
        "numero": "DS 1356",
        "fecha": "2012-09-22",
        "titulo": "Regulación de Azucar",
        "archivo": "pdf/DS_1356_de_22-09-2012.pdf",
        "descripcion": "El presente Decreto Supremo, tiene por objeto autorizar de manera excepcional la exportación de azúcar previa verificación de suficiencia de abastecimiento en el mercado interno a precio justo",
        "seccion_de_norma_id": "1"
    },
    {
        "numero": "DS 1316",
        "fecha": "2012-10-08",
        "titulo": "Regulación de Ganado vacuno",
        "archivo": "pdf/DS_1316_de_08-10-2012.pdf",
        "descripcion": "El presente Decreto Supremo tiene por objeto autorizar de manera excepcional la exportación de ganado bovino reproductor, previa certificación de suficiencia y abastecimiento en el mercado interno",
        "seccion_de_norma_id": "1"
    },
    {
        "numero": "DS 1383",
        "fecha": "2012-10-17",
        "titulo": "Regulación de Sorgo-Maiz",
        "archivo": "pdf/DS_1383_de_17-10-2012.pdf",
        "descripcion": "El presente Decreto Supremo tiene por objeto ampliar los cupos de exportación para los excedentes de producción de maíz amarillo duro y sorgo",
        "seccion_de_norma_id": "1"
    },
    {
        "numero": "DS 1514",
        "fecha": "2013-03-06",
        "titulo": "Regulación de Soya",
        "archivo": "pdf/DS_1514_de_06-03-2013.pdf",
        "descripcion": "Se autoriza de manera excepcionalmente previa verificación de suficiencia de abastecimiento interno a precio justo, la exportación de hasta cuatrocientas mil toneladas métricas (400.000 TM.), adicionales a las autorizadas mediante Decreto Supremo Nro. 1283, de 4 de julio de 2012, de los productos identificados en las siguientes subpartidas arancelarias",
        "seccion_de_norma_id": "1"
    },
    {
        "numero": "DS 1637",
        "fecha": "2013-07-10",
        "titulo": "Regulación de Carne de res-Sorgo-Soya",
        "archivo": "pdf/DS_1637_de_10-07-2013.pdf",
        "descripcion": "El presente Decreto Supremo tiene por objeto ampliar los cupos de exportación de carne de res y sorgo",
        "seccion_de_norma_id": "1"
    },
    {
        "numero": "DS 1925",
        "fecha": "2014-03-12",
        "titulo": "Regulación de Soya",
        "archivo": "pdf/DS_1925_de_12-03-2014.pdf",
        "descripcion": "Se amplía el cupo de exportación de soya en grano en trescientas mil (300.000) toneladas métricas adicionales a lo establecido mediante Decreto Supremo Nro. 1514, de 6 de marzo de 2013, ampliado por el Artículo 4 del Decreto Supremo Nro. 1637, de 10 de julio de 2013, previa verificación de suficiencia y abastecimiento en el mercado interno a precio justo de los productos clasificados en las siguientes subpartidas arancelarias",
        "seccion_de_norma_id": "1"
    },
    {
        "numero": "DS 2391",
        "fecha": "2015-06-03",
        "titulo": "Regulación de Maiz",
        "archivo": "pdf/DS_2391_de_03-06-2015.pdf",
        "descripcion": "El presente Decreto Supremo tiene por objeto ampliar el cupo de exportación para el excedente de producción de maíz amarillo duro y autorizar la exportación de los subproductos de maíz",
        "seccion_de_norma_id": "1"
    },
    {
        "numero": "DS 2489",
        "fecha": "2015-08-19",
        "titulo": "Regulación de Carne de res",
        "archivo": "pdf/DS_2489_de_19-08-2015.pdf",
        "descripcion": "El presente Decreto Supremo tiene por objeto ampliar el cupo de exportación para el excedente de carne de res",
        "seccion_de_norma_id": "1"
    },
    {
        "numero": "RESOLUCION 1324",
        "fecha": "2010-05-28",
        "titulo": "RESOLUCION 1324",
        "archivo": "",
        "descripcion": "ACTUALIZACIÓN DE LA NÓMINA DE BIENES NO PRODUCIDOS EN LA SUBREGIÓN Y DE LA NÓMINA DE PRODUCCIÓN EXCLUSIVA DEL PERÚ",
        "seccion_de_norma_id": "2"
    },
    {
        "numero": "RESOLUCION 1320",
        "fecha": "2010-04-30",
        "titulo": "RESOLUCION 1320",
        "archivo": "",
        "descripcion": "ACTUALIZACIÓN DE LA NÓMINA DE BIENES NO PRODUCIDOS EN LA SUBREGIÓN Y DE LA NÓMINA DE PRODUCCIÓN EXCLUSIVA DEL PERÚ",
        "seccion_de_norma_id": "2"
    },
    {
        "numero": "Nro. 47",
        "fecha": "2008-03-07",
        "titulo": "ACUERDO DE COMPLEMENTACIÓN ECONÓMICA",
        "archivo": "",
        "descripcion": "Los Plenipotenciarios de la República de Bolivia y de la República de Cuba, acreditados por sus respectivos Gobiernos según poderes que fueron otorgados en buena y debida forma, depositados oportunamente en la Secretaría General de la Asociación Latinoamericana de Integración (ALADI)",
        "seccion_de_norma_id": "2"
    },
    {
        "numero": "NNN",
        "fecha": "1993-04-06",
        "titulo": "ACUERDO DE COMPLEMENTACIÓN ECONÓMICA ENTRE BOLIVIA Y CHILE",
        "archivo": "",
        "descripcion": "Acuerdo de ComplementaciÓn Económica, de conformidad con lo establecido en el Tratado de Montevideo 1980 y la Resolución 2 del Consejo de Ministros de la ALALC",
        "seccion_de_norma_id": "2"
    }
]